mqtt_presence_checker/__init__.py
mqtt_presence_checker/__main__.py
mqtt_presence_checker/minuterie.py
mqtt_presence_checker/mqtt.py
mqtt_presence_checker/ping.py
mqtt_presence_checker/util.py
mqtt_presence_checker-0.1.18.dist-info/entry_points.txt
mqtt_presence_checker-0.1.18.dist-info/LICENSE.md
mqtt_presence_checker-0.1.18.dist-info/WHEEL
mqtt_presence_checker-0.1.18.dist-info/METADATA
mqtt_presence_checker-0.1.18.dist-info/RECORD
