Metadata-Version: 2.1
Name: mqtt-presence-checker
Version: 0.1.18
Summary: Check if you (or your phone) is at home and notify your smarthome via mqtt!
Author: RincewindWizzard
Author-email: git@magierdinge.de
Requires-Python: >=3.10,<4.0
Classifier: Programming Language :: Python :: 3
Classifier: Programming Language :: Python :: 3.10
Classifier: Programming Language :: Python :: 3.11
Provides-Extra: docs
Requires-Dist: asyncio-mqtt (>=0.13.0,<0.14.0)
Requires-Dist: docstring-parser (>=0.15,<0.16)
Requires-Dist: dotwiz (>=0.4.0,<0.5.0)
Requires-Dist: jsonargparse (>=4.15.1,<5.0.0)
Requires-Dist: loguru (>=0.6.0,<0.7.0)
Requires-Dist: pingparsing (>=1.4.0,<2.0.0)
Requires-Dist: pytest (>=7.1.3,<8.0.0)
Requires-Dist: python-daemon (>=2.3.1,<3.0.0)
Requires-Dist: sphinx (>=5.3.0,<6.0.0); extra == "docs"
Requires-Dist: sphinx-rtd-theme (>=1.0.0,<2.0.0); extra == "docs"
Requires-Dist: sphinxcontrib-napoleon (>=0.7,<0.8); extra == "docs"
Requires-Dist: toml (>=0.10.2,<0.11.0)
